axgrad/__init__.py
axgrad/_core.py
axgrad/autograd/functions.py
axgrad/axgrad/__init__.py
axgrad/axgrad/_core.py
axgrad/axgrad/autograd/functions.py
axgrad/axgrad/helpers.py
axgrad/axgrad/libtensor.dll.a
axgrad/axgrad/libtensor.pyd
axgrad/axgrad/nn/__init__.py
axgrad/axgrad/nn/functional.py
axgrad/axgrad/nn/loss.py
axgrad/axgrad/nn/module.py
axgrad/axgrad/nn/modules/linear.py
axgrad/axgrad/nn/optim.py
axgrad/axgrad/nn/parameter.py
axgrad/axgrad/tensor.py
axgrad/axgrad/utils.py
axgrad/csrc/binary_ops.cpp
axgrad/csrc/binary_ops.h
axgrad/csrc/core/contiguous.cpp
axgrad/csrc/core/contiguous.h
axgrad/csrc/core/core.cpp
axgrad/csrc/core/core.h
axgrad/csrc/core/dtype.cpp
axgrad/csrc/core/dtype.h
axgrad/csrc/cpu/helpers.cpp
axgrad/csrc/cpu/helpers.h
axgrad/csrc/cpu/ops_binary.cpp
axgrad/csrc/cpu/ops_binary.h
axgrad/csrc/cpu/ops_redux.cpp
axgrad/csrc/cpu/ops_redux.h
axgrad/csrc/cpu/ops_shape.cpp
axgrad/csrc/cpu/ops_shape.h
axgrad/csrc/cpu/ops_tensor.cpp
axgrad/csrc/cpu/ops_tensor.h
axgrad/csrc/cpu/ops_unary.cpp
axgrad/csrc/cpu/ops_unary.h
axgrad/csrc/cuda/cuda.cu
axgrad/csrc/cuda/cuda.cuh
axgrad/csrc/cuda/kernels/binary_ops_kernel.cu
axgrad/csrc/cuda/kernels/binary_ops_kernel.cuh
axgrad/csrc/cuda/kernels/matmul_kernel.cu
axgrad/csrc/cuda/kernels/matmul_kernel.cuh
axgrad/csrc/cuda/kernels/red_ops_kernel.cu
axgrad/csrc/cuda/kernels/red_ops_kernel.cuh
axgrad/csrc/cuda/kernels/shape_kernel.cu
axgrad/csrc/cuda/kernels/shape_kernel.cuh
axgrad/csrc/cuda/kernels/stats_ops_kernel.cu
axgrad/csrc/cuda/kernels/stats_ops_kernel.cuh
axgrad/csrc/cuda/kernels/unary_ops_kernel.cu
axgrad/csrc/cuda/kernels/unary_ops_kernel.cuh
axgrad/csrc/inc/random.h
axgrad/csrc/redux_ops.cpp
axgrad/csrc/redux_ops.h
axgrad/csrc/shape_ops.cpp
axgrad/csrc/shape_ops.h
axgrad/csrc/tensor_ops.cpp
axgrad/csrc/tensor_ops.h
axgrad/csrc/unary_ops.cpp
axgrad/csrc/unary_ops.h
axgrad/csrc/utils.cpp
axgrad/csrc/utils.h
axgrad/helpers.py
axgrad/nn/__init__.py
axgrad/nn/functional.py
axgrad/nn/loss.py
axgrad/nn/module.py
axgrad-0.0.1.dist-info/METADATA
axgrad-0.0.1.dist-info/WHEEL
axgrad-0.0.1.dist-info/RECORD
