Metadata-Version: 2.2
Name: axgrad
Version: 0.0.1
Summary: lightweight tensor library with autograd engine for training deep neural nets
Keywords: neural networks,automatic differentiation,deep learning,machine learning
Author-Email: Shivendra S <shivharsh44@gmail.com>
Maintainer-Email: Shivendra S <shivharsh44@gmail.com>
License: Apache-2.0
Classifier: Development Status :: 2 - Pre-Alpha
Classifier: Intended Audience :: Developers
Classifier: Intended Audience :: Science/Research
Classifier: Programming Language :: Python :: 3
Classifier: Programming Language :: Python :: 3.11
Classifier: Programming Language :: Python :: 3.12
Classifier: Topic :: Scientific/Engineering :: Artificial Intelligence
Classifier: Topic :: Scientific/Engineering :: Mathematics
Project-URL: Repository, https://github.com/shivendrra/axgrad
Project-URL: Documentation, https://github.com/shivendrra/axgrad/tree/main/docs/User.md
Project-URL: Bug Tracker, https://github.com/shivendrra/axgrad/issues
Requires-Python: >=3.11
Requires-Dist: numpy>=1.20.0
Requires-Dist: matplotlib>=3.5.0
